cmc/__init__.py
cmc/coinmarketcap.py
cmc/asynchro/__init__.py
cmc/asynchro/async_utils.py
cmc/utils/__init__.py
cmc/utils/utils.py
cmc-2.0.3.1.dist-info/LICENSE
cmc-2.0.3.1.dist-info/METADATA
cmc-2.0.3.1.dist-info/WHEEL
cmc-2.0.3.1.dist-info/entry_points.txt
cmc-2.0.3.1.dist-info/top_level.txt
cmc-2.0.3.1.dist-info/RECORD
