Metadata-Version: 2.1
Name: cmc
Version: 2.0.3.1
Summary: Get the price history for CoinMarketCap-listed currencies
Home-page: https://github.com/Alescontrela/coinmarketcap-history
Author: Alejandro Escontrela <alejandroescontrela@gmail.com>,Felipe Faria <felipefaria@me.com>
Author-email: alejandroescontrela@gmail.com
License: UNKNOWN
Platform: UNKNOWN
Classifier: Programming Language :: Python :: 3
Classifier: License :: OSI Approved :: MIT License
Classifier: Operating System :: OS Independent
Requires-Dist: aiohttp
Requires-Dist: aiodns
Requires-Dist: pandas
Requires-Dist: tqdm
Requires-Dist: requests
Requires-Dist: asyncio ; python_version < "3.4"
